chesshub/__init__.py
chesshub/_internal/__init__.py
chesshub/_internal/models/__init__.py
chesshub/_internal/models/board.py
chesshub/_internal/models/piece.py
chesshub/_internal/models/square.py
chesshub/games/__init__.py
chesshub-0.0.2.dist-info/LICENSE
chesshub-0.0.2.dist-info/METADATA
chesshub-0.0.2.dist-info/WHEEL
chesshub-0.0.2.dist-info/top_level.txt
chesshub-0.0.2.dist-info/RECORD
